edward2/__init__.py
edward2/trace.py
edward2/trace_test.py
edward2/tracers.py
edward2/tracers_test.py
edward2/version.py
edward2/numpy/__init__.py
edward2/numpy/generated_random_variables.py
edward2/numpy/generated_random_variables_test.py
edward2/numpy/program_transformations.py
edward2/numpy/program_transformations_test.py
edward2/tensorflow/__init__.py
edward2/tensorflow/constraints.py
edward2/tensorflow/constraints_test.py
edward2/tensorflow/generated_random_variables.py
edward2/tensorflow/generated_random_variables_test.py
edward2/tensorflow/initializers.py
edward2/tensorflow/initializers_test.py
edward2/tensorflow/program_transformations.py
edward2/tensorflow/program_transformations_test.py
edward2/tensorflow/random_variable.py
edward2/tensorflow/random_variable_test.py
edward2/tensorflow/regularizers.py
edward2/tensorflow/regularizers_test.py
edward2/tensorflow/transformed_random_variable.py
edward2/tensorflow/transformed_random_variable_test.py
edward2/tensorflow/layers/__init__.py
edward2/tensorflow/layers/bayesian_linear_model.py
edward2/tensorflow/layers/bayesian_linear_model_test.py
edward2/tensorflow/layers/convolutional.py
edward2/tensorflow/layers/convolutional_test.py
edward2/tensorflow/layers/dense.py
edward2/tensorflow/layers/dense_test.py
edward2/tensorflow/layers/discrete_flows.py
edward2/tensorflow/layers/discrete_flows_test.py
edward2/tensorflow/layers/embeddings.py
edward2/tensorflow/layers/embeddings_test.py
edward2/tensorflow/layers/gaussian_process.py
edward2/tensorflow/layers/gaussian_process_test.py
edward2/tensorflow/layers/heteroscedastic.py
edward2/tensorflow/layers/heteroscedastic_test.py
edward2/tensorflow/layers/made.py
edward2/tensorflow/layers/made_test.py
edward2/tensorflow/layers/neural_process.py
edward2/tensorflow/layers/neural_process_test.py
edward2/tensorflow/layers/noise.py
edward2/tensorflow/layers/noise_test.py
edward2/tensorflow/layers/normalization.py
edward2/tensorflow/layers/normalization_test.py
edward2-0.0.2.dist-info/AUTHORS
edward2-0.0.2.dist-info/LICENSE
edward2-0.0.2.dist-info/METADATA
edward2-0.0.2.dist-info/WHEEL
edward2-0.0.2.dist-info/top_level.txt
edward2-0.0.2.dist-info/RECORD
